petit_interfacer/__init__.py
petit_interfacer/exceptions.py
petit_interfacer/prototype_transformer.py
petit_interfacer/utils.py
petit_interfacer-0.1.4.dist-info/LICENSE.txt
petit_interfacer-0.1.4.dist-info/METADATA
petit_interfacer-0.1.4.dist-info/WHEEL
petit_interfacer-0.1.4.dist-info/top_level.txt
petit_interfacer-0.1.4.dist-info/RECORD
