Metadata-Version: 2.1
Name: petit-interfacer
Version: 0.1.4
Summary: Convert your function prototypes to work faster
Home-page: https://github.com/Plawn/petit_interfacer
Author: Plawn
Author-email: plawn.yay@gmail.com
License: apache-2.0
Platform: UNKNOWN
Requires-Python: >=3.8
